animal_classifier/__init__.py
animal_classifier-1.0.5.dist-info/LICENSE
animal_classifier-1.0.5.dist-info/METADATA
animal_classifier-1.0.5.dist-info/WHEEL
animal_classifier-1.0.5.dist-info/top_level.txt
animal_classifier-1.0.5.dist-info/RECORD
