Metadata-Version: 2.1
Name: animal-classifier
Version: 1.0.5
Summary: It classify the cat or dog images
Home-page: https://github.com/xvinay28x/animal_classifier_library
Author: Vinay Garg
Author-email: xvinay28x@gmail.com
License: UNKNOWN
Platform: UNKNOWN
Classifier: License :: OSI Approved :: MIT License
Classifier: Programming Language :: Python :: 3.6
Classifier: Programming Language :: Python :: 3.7
Classifier: Programming Language :: Python :: 3.8
Requires-Dist: tensorflow
